LICENSE
MANIFEST.in
README.md
setup.py
bin/blackdog
blackdog/__init__.py
blackdog/bukkitdev.py
blackdog/config.py
blackdog/exception.py
blackdog/plugin.py
blackdog/server.py
blackdog.egg-info/PKG-INFO
blackdog.egg-info/SOURCES.txt
blackdog.egg-info/dependency_links.txt
blackdog.egg-info/requires.txt
blackdog.egg-info/top_level.txt