Metadata-Version: 1.1
Name: blackdog
Version: 1.0.2
Summary: A bukkitdev to maven repository mapper
Home-page: http://github.com/Snaipe/BlackDog.git
Author: Snaipe, Therozin
Author-email: franklinmathieu@gmail.com
License: GPLv3
Keywords: minecraft bukkitdev plugin maven repository
Platform: UNKNOWN
Classifier: Development Status :: 5 - Production/Stable
Classifier: Environment :: Console
Classifier: License :: OSI Approved :: GNU General Public License v3 or later (GPLv3+)
Classifier: Operating System :: POSIX
Classifier: Programming Language :: Python :: 3.4
Classifier: Topic :: System :: Systems Administration
Classifier: Topic :: Utilities
